dogcrud/__about__.py
dogcrud/__init__.py
dogcrud/py.typed
dogcrud/cli/__init__.py
dogcrud/cli/list.py
dogcrud/cli/main.py
dogcrud/cli/open.py
dogcrud/cli/restore.py
dogcrud/cli/save.py
dogcrud/core/__init__.py
dogcrud/core/context.py
dogcrud/core/data.py
dogcrud/core/logging.py
dogcrud/core/metric_metadata_resource_type.py
dogcrud/core/metric_resource_type.py
dogcrud/core/metrics.py
dogcrud/core/pagination.py
dogcrud/core/reference_table_resource_type.py
dogcrud/core/resource_type.py
dogcrud/core/resource_type_registry.py
dogcrud/core/rest.py
dogcrud/core/standard_resource_type.py
dogcrud/core/transformers.py
dogcrud-1.6.0.dist-info/METADATA
dogcrud-1.6.0.dist-info/WHEEL
dogcrud-1.6.0.dist-info/entry_points.txt
dogcrud-1.6.0.dist-info/licenses/LICENSE.txt
dogcrud-1.6.0.dist-info/RECORD
