Metadata-Version: 2.4
Name: dogcrud
Version: 1.6.0
Summary: Datadog CRUD resources from the command line.
Project-URL: Documentation, https://github.com/drichardson/dogcrud
Project-URL: Issues, https://github.com/drichardson/dogcrud/issues
Project-URL: Source, https://github.com/drichardson/dogcrud.git
Author-email: Doug Richardson <git@rekt.email>
License-File: LICENSE.txt
Keywords: cli,datadog
Classifier: Development Status :: 4 - Beta
Classifier: Intended Audience :: Developers
Classifier: License :: OSI Approved :: MIT License
Classifier: Programming Language :: Python :: 3.12
Classifier: Programming Language :: Python :: 3.13
Classifier: Topic :: System :: Monitoring
Requires-Python: <3.14,>=3.12
Requires-Dist: aiofiles~=24.1.0
Requires-Dist: aiohttp[speedups]~=3.11.11
Requires-Dist: click~=8.1.8
Requires-Dist: orjson~=3.10.13
Requires-Dist: pydantic~=2.10.4
